blazeserve/__init__.py
blazeserve/cli.py
blazeserve/logging.py
blazeserve/server.py
blazeserve/utils.py
blazeserve-0.2.0.dist-info/licenses/LICENSE
blazeserve-0.2.0.dist-info/METADATA
blazeserve-0.2.0.dist-info/WHEEL
blazeserve-0.2.0.dist-info/entry_points.txt
blazeserve-0.2.0.dist-info/top_level.txt
blazeserve-0.2.0.dist-info/RECORD
