Metadata-Version: 2.4
Name: blazeserve
Version: 0.2.0
Summary: ⚡ Ultra-fast HTTP file server with advanced performance optimizations, real-time metrics, and production-ready architecture — supports byte-range/multi-range downloads, TLS, Basic Auth, throttling, uploads, streaming ZIP, CORS, and a polished CLI.
Author: Jaydeep Solanki
License: MIT
Project-URL: Homepage, https://github.com/whoisjayd/blazeserve
Project-URL: Repository, https://github.com/whoisjayd/blazeserve.git
Project-URL: Issues, https://github.com/whoisjayd/blazeserve/issues
Keywords: http,file-server,range,resume,download,cli,rich,click,cors,zip,throttle
Classifier: Development Status :: 5 - Production/Stable
Classifier: Programming Language :: Python :: 3
Classifier: Programming Language :: Python :: 3 :: Only
Classifier: Programming Language :: Python :: 3.9
Classifier: Programming Language :: Python :: 3.10
Classifier: Programming Language :: Python :: 3.11
Classifier: Programming Language :: Python :: 3.12
Classifier: License :: OSI Approved :: MIT License
Classifier: Operating System :: OS Independent
Classifier: Topic :: Internet :: WWW/HTTP :: HTTP Servers
Classifier: Topic :: System :: Networking
Requires-Python: >=3.9
License-File: LICENSE
Requires-Dist: click>=8.1
Requires-Dist: rich>=13.0.0
Requires-Dist: rich-click>=1.8.0
Provides-Extra: dev
Requires-Dist: pytest>=8.0; extra == "dev"
Requires-Dist: mypy>=1.7; extra == "dev"
Requires-Dist: ruff>=0.5; extra == "dev"
Requires-Dist: types-click>=7.1.8; extra == "dev"
Dynamic: license-file
